setup.py
wikidata_suggest.py
scripts/wd
wikidata_suggest.egg-info/PKG-INFO
wikidata_suggest.egg-info/SOURCES.txt
wikidata_suggest.egg-info/dependency_links.txt
wikidata_suggest.egg-info/requires.txt
wikidata_suggest.egg-info/top_level.txt