Metadata-Version: 1.0
Name: wikidata-suggest
Version: 0.0.7
Summary: Interactively look up Wikidata entities from the command line
Home-page: http://github.com/edsu/wikidata_suggest
Author: Ed Summers
Author-email: ehs@pobox.com
License: MIT License
Platform: UNKNOWN
